{"stats":{"minecraft:used":{"boring:black_diamond_helmet":1,"boring:black_diamond_boots":1,"minecraft:damaged_anvil":49,"minecraft:chipped_anvil":52,"boring:black_diamond_hammer":31,"boring:black_diamond_leggings":1,"minecraft:bedrock":34,"minecraft:anvil":42,"boring:black_diamond_chestplate":1},"minecraft:killed":{"minecraft:horse":6,"minecraft:sheep":12,"minecraft:cat":4,"minecraft:skeleton":14,"minecraft:zombie":18,"minecraft:pig":6,"minecraft:chicken":12,"minecraft:spider":21,"minecraft:iron_golem":2,"minecraft:bat":1,"minecraft:player":1,"minecraft:villager":3,"minecraft:slime":588,"minecraft:creeper":21,"minecraft:cow":4},"minecraft:custom":{"minecraft:time_since_rest":4771,"minecraft:sprint_one_cm":1353,"minecraft:damage_taken":510,"minecraft:walk_one_cm":10225,"minecraft:mob_kills":712,"minecraft:interact_with_anvil":8,"minecraft:damage_dealt":410,"minecraft:player_kills":1,"minecraft:fly_one_cm":34459,"minecraft:crouch_one_cm":1403,"minecraft:play_time":11125,"minecraft:deaths":1,"minecraft:sneak_time":1684,"minecraft:jump":178,"minecraft:leave_game":1,"minecraft:time_since_death":4746,"minecraft:total_world_time":11343,"minecraft:fall_one_cm":1820},"minecraft:picked_up":{"minecraft:anvil":3,"minecraft:bedrock":1,"boring:black_diamond_hammer":1,"minecraft:dirt":2,"minecraft:chipped_anvil":24,"minecraft:slime_ball":2,"minecraft:damaged_anvil":10},"minecraft:mined":{"minecraft:fire":2,"minecraft:grass_block":4,"minecraft:dirt":3,"minecraft:damaged_anvil":4,"minecraft:chipped_anvil":16}},"DataVersion":3700}